cloud4rpi/__init__.py
cloud4rpi/config.py
cloud4rpi/device.py
cloud4rpi/errors.py
cloud4rpi/mqtt_api.py
cloud4rpi/utils.py
cloud4rpi/utils_v2.py
cloud4rpi/utils_v3.py
cloud4rpi/version.py
cloud4rpi-1.1.2.dist-info/LICENSE
cloud4rpi-1.1.2.dist-info/METADATA
cloud4rpi-1.1.2.dist-info/WHEEL
cloud4rpi-1.1.2.dist-info/top_level.txt
cloud4rpi-1.1.2.dist-info/RECORD
